pg_sui-1.7.4.dist-info/licenses/LICENSE
pgsui/__init__.py
pgsui/_version.py
pgsui/cli.py
pgsui/data_processing/__init__.py
pgsui/data_processing/config.py
pgsui/data_processing/containers.py
pgsui/data_processing/transformers.py
pgsui/electron/bootstrap.py
pgsui/electron/launch.py
pgsui/electron/package.json
pgsui/electron/app/__init__.py
pgsui/electron/app/__main__.py
pgsui/electron/app/main.js
pgsui/electron/app/package-lock.json
pgsui/electron/app/package.json
pgsui/electron/app/preload.js
pgsui/electron/app/server.py
pgsui/electron/app/extra-resources/.gitkeep
pgsui/electron/app/icons/icons/1024x1024.png
pgsui/electron/app/icons/icons/128x128.png
pgsui/electron/app/icons/icons/16x16.png
pgsui/electron/app/icons/icons/24x24.png
pgsui/electron/app/icons/icons/256x256.png
pgsui/electron/app/icons/icons/32x32.png
pgsui/electron/app/icons/icons/48x48.png
pgsui/electron/app/icons/icons/512x512.png
pgsui/electron/app/icons/icons/64x64.png
pgsui/electron/app/icons/icons/icon.icns
pgsui/electron/app/icons/icons/icon.ico
pgsui/electron/app/ui/logo.png
pgsui/electron/app/ui/renderer.js
pgsui/electron/app/ui/styles.css
pgsui/electron/app/ui/ui_shim.js
pgsui/example_data/__init__.py
pgsui/example_data/phylip_files/__init__.py
pgsui/example_data/phylip_files/test.phy
pgsui/example_data/popmaps/__init__.py
pgsui/example_data/popmaps/phylogen_nomx.popmap
pgsui/example_data/structure_files/__init__.py
pgsui/example_data/structure_files/test.pops.2row.allsites.str
pgsui/example_data/vcf_files/phylogen_subset14K.vcf.gz
pgsui/example_data/vcf_files/phylogen_subset14K.vcf.gz.tbi
pgsui/impute/__init__.py
pgsui/impute/deterministic/imputers/allele_freq.py
pgsui/impute/deterministic/imputers/mode.py
pgsui/impute/deterministic/imputers/nmf.py
pgsui/impute/deterministic/imputers/phylo.py
pgsui/impute/deterministic/imputers/ref_allele.py
pgsui/impute/supervised/__init__.py
pgsui/impute/supervised/base.py
pgsui/impute/supervised/imputers/__init__.py
pgsui/impute/supervised/imputers/hist_gradient_boosting.py
pg_sui-1.7.4.dist-info/METADATA
pg_sui-1.7.4.dist-info/WHEEL
pg_sui-1.7.4.dist-info/entry_points.txt
pg_sui-1.7.4.dist-info/top_level.txt
pg_sui-1.7.4.dist-info/RECORD
