Metadata-Version: 2.4
Name: pg-sui
Version: 1.7.4
Summary: Python machine and deep learning API to impute missing genotypes
Author-email: "Drs. Bradley T. Martin and Tyler K. Chafin" <evobio721@gmail.com>
Maintainer-email: "Dr. Bradley T. Martin" <evobio721@gmail.com>
License: GNU General Public License v3 (GPLv3)
Project-URL: Homepage, https://github.com/btmartin721/PG-SUI
Project-URL: Documentation, https://pg-sui.readthedocs.io/en/latest/
Project-URL: Source, https://github.com/btmartin721/PG-SUI.git
Project-URL: BugTracker, https://github.com/btmartin721/PG-SUI/issues
Keywords: impute,imputation,AI,deep learning,machine learning,neural network,vae,autoencoder,ubp,nlpca,population genetics,unsupervised,supervised,bioinformatics,snp,genomics,genotype,missing data,data analysis,data science,statistics,data visualization,python
Classifier: Programming Language :: Python :: 3
Classifier: Programming Language :: Python :: 3.11
Classifier: Programming Language :: Python :: 3.12
Classifier: Development Status :: 4 - Beta
Classifier: Environment :: Console
Classifier: Intended Audience :: Science/Research
Classifier: Intended Audience :: Developers
Classifier: Intended Audience :: Education
Classifier: License :: OSI Approved :: GNU General Public License v3 (GPLv3)
Classifier: Topic :: Scientific/Engineering :: Bio-Informatics
Classifier: Topic :: Scientific/Engineering :: Artificial Intelligence
Classifier: Topic :: Scientific/Engineering :: Information Analysis
Classifier: Topic :: Scientific/Engineering :: Visualization
Classifier: Operating System :: MacOS
Classifier: Operating System :: MacOS :: MacOS X
Classifier: Operating System :: Unix
Classifier: Operating System :: POSIX
Classifier: Natural Language :: English
Requires-Python: >=3.11
License-File: LICENSE
Requires-Dist: matplotlib
Requires-Dist: numpy>=2.1
Requires-Dist: pandas>=2.2.2
Requires-Dist: scikit-learn>=1.4
Requires-Dist: scipy
Requires-Dist: seaborn
Requires-Dist: torch
Requires-Dist: tqdm
Requires-Dist: toytree
Requires-Dist: optuna
Requires-Dist: rich
Requires-Dist: rich[jupyter]
Requires-Dist: snpio
Provides-Extra: intel
Requires-Dist: scikit-learn-intelex; extra == "intel"
Provides-Extra: docs
Requires-Dist: sphinx; extra == "docs"
Requires-Dist: sphinx-rtd-theme; extra == "docs"
Requires-Dist: sphinxcontrib-napoleon; extra == "docs"
Requires-Dist: sphinxcontrib-programoutput; extra == "docs"
Provides-Extra: dev
Requires-Dist: twine; extra == "dev"
Requires-Dist: wheel; extra == "dev"
Requires-Dist: pytest; extra == "dev"
Requires-Dist: sphinx; extra == "dev"
Requires-Dist: sphinx-rtd-theme; extra == "dev"
Requires-Dist: sphinxcontrib-napoleon; extra == "dev"
Requires-Dist: sphinxcontrib-programoutput; extra == "dev"
Requires-Dist: requests; extra == "dev"
Provides-Extra: optional
Requires-Dist: PyObjC; extra == "optional"
Provides-Extra: gui
Requires-Dist: fastapi>=0.110; extra == "gui"
Requires-Dist: uvicorn[standard]>=0.23; extra == "gui"
Dynamic: license-file
